[
  {
    "id": "01",
    "name": "ETS 2024 - Test 1"
  },
  {
    "id": "02",
    "name": "ETS 2024 - Test 2"
  },
  {
    "id": "03",
    "name": "ETS 2024 - Test 3"
  },
  {
    "id": "04",
    "name": "ETS 2024 - Test 4"
  },
  {
    "id": "05",
    "name": "ETS 2024 - Test 5"
  },
  {
    "id": "06",
    "name": "ETS 2024 - Test 6"
  },
  {
    "id": "07",
    "name": "ETS 2024 - Test 7"
  },
  {
    "id": "08",
    "name": "ETS 2024 - Test 8"
  },
  {
    "id": "09",
    "name": "ETS 2024 - Test 9"
  },
  {
    "id": "10",
    "name": "ETS 2024 - Test 10"
  }
]
